bavli_pages/__init__.py
bavli_pages/all_pages.xlsx
bavli_pages/bavli.py
bavli_pages/chapter_view.xlsx
bavli_pages/pages_view.xlsx
bavli_pages-0.2.0.dist-info/LICENSE
bavli_pages-0.2.0.dist-info/METADATA
bavli_pages-0.2.0.dist-info/WHEEL
bavli_pages-0.2.0.dist-info/top_level.txt
bavli_pages-0.2.0.dist-info/RECORD
