Metadata-Version: 2.1
Name: bavli-pages
Version: 0.2.0
Summary: List of pages per Masechet at each chapter at the Jewish Talmud/Gemara/Shas Bavli
Home-page: https://github.com/lisrael1/bavli_pages
Author: Lior Israeli
Author-email: israelilior@gmail.com
License: UNKNOWN
Project-URL: Bug Tracker, https://github.com/lisrael1/bavli_pages/issues
Platform: UNKNOWN
Classifier: Programming Language :: Python :: 3
Classifier: License :: OSI Approved :: MIT License
Classifier: Operating System :: OS Independent
Requires-Python: >=3.6
License-File: LICENSE
Requires-Dist: pandas
Requires-Dist: gematriapy
